wirepas_messaging/__about__.py
wirepas_messaging/__init__.py
wirepas_messaging/__main__.py
wirepas_messaging/gateway/__init__.py
wirepas_messaging/gateway/config_message_pb2.py
wirepas_messaging/gateway/config_message_pb2_grpc.py
wirepas_messaging/gateway/data_message_pb2.py
wirepas_messaging/gateway/data_message_pb2_grpc.py
wirepas_messaging/gateway/error_pb2.py
wirepas_messaging/gateway/error_pb2_grpc.py
wirepas_messaging/gateway/generic_message_pb2.py
wirepas_messaging/gateway/generic_message_pb2_grpc.py
wirepas_messaging/gateway/otap_message_pb2.py
wirepas_messaging/gateway/otap_message_pb2_grpc.py
wirepas_messaging/gateway/wp_global_pb2.py
wirepas_messaging/gateway/wp_global_pb2_grpc.py
wirepas_messaging/gateway/api/__init__.py
wirepas_messaging/gateway/api/config_helper.py
wirepas_messaging/gateway/api/event.py
wirepas_messaging/gateway/api/gateway_result_code.py
wirepas_messaging/gateway/api/get_configs.py
wirepas_messaging/gateway/api/get_gw_info.py
wirepas_messaging/gateway/api/get_scratchpad_status.py
wirepas_messaging/gateway/api/otap_helper.py
wirepas_messaging/gateway/api/process_scratchpad.py
wirepas_messaging/gateway/api/received_data.py
wirepas_messaging/gateway/api/request.py
wirepas_messaging/gateway/api/response.py
wirepas_messaging/gateway/api/send_data.py
wirepas_messaging/gateway/api/set_config.py
wirepas_messaging/gateway/api/status.py
wirepas_messaging/gateway/api/upload_scratchpad.py
wirepas_messaging/gateway/api/wirepas_exceptions.py
wirepas_messaging/nanopb/__init__.py
wirepas_messaging/nanopb/nanopb_pb2.py
wirepas_messaging/nanopb/nanopb_pb2_grpc.py
wirepas_messaging/wnt/__init__.py
wirepas_messaging/wnt/commons_pb2.py
wirepas_messaging/wnt/commons_pb2_grpc.py
wirepas_messaging/wnt/internal_pb2.py
wirepas_messaging/wnt/internal_pb2_grpc.py
wirepas_messaging/wnt/message_pb2.py
wirepas_messaging/wnt/message_pb2_grpc.py
wirepas_messaging/wnt/otap_pb2.py
wirepas_messaging/wnt/otap_pb2_grpc.py
wirepas_messaging/wnt/positioning_pb2.py
wirepas_messaging-1.4.0.dist-info/LICENSE
wirepas_messaging-1.4.0.dist-info/METADATA
wirepas_messaging-1.4.0.dist-info/WHEEL
wirepas_messaging-1.4.0.dist-info/top_level.txt
wirepas_messaging-1.4.0.dist-info/RECORD
