Metadata-Version: 2.1
Name: wirepas-messaging
Version: 1.4.0
Summary: Wrapper interfaces to interact with Wirepas APIs.
Home-page: https://github.com/wirepas/backend-apis/tree/master/wrappers/python
Author: Wirepas Ltd
Author-email: opensource@wirepas.com
License: Apache-2
Keywords: wirepas connectivity iot mesh
Platform: UNKNOWN
Classifier: Development Status :: 5 - Production/Stable
Classifier: Intended Audience :: Developers
Classifier: License :: OSI Approved :: Apache Software License
Classifier: Topic :: Software Development :: Libraries
Classifier: Programming Language :: Python :: 3
Requires-Dist: grpcio (==1.23.0)
Requires-Dist: protobuf (==3.10.0)
Provides-Extra: examples
Requires-Dist: websocket-client (==0.48.0) ; extra == 'examples'
Requires-Dist: PyYAML (==5.1.2) ; extra == 'examples'
